game_theory_lab-0.1.3.dist-info/licenses/LICENSE.md
gametheorylab/__init__.py
gametheorylab/auctiongt/__init__.py
gametheorylab/axelrod_interactive/__init__.py
gametheorylab/axelrod_interactive/arena.py
gametheorylab/axelrod_interactive/result.py
gametheorylab/axelrod_interactive/settings.py
gametheorylab/axelrod_interactive/strategy.py
gametheorylab/axelrod_interactive/tournament.py
gametheorylab/axelrod_interactive/strategies/__init__.py
gametheorylab/axelrod_interactive/strategies/adaptive_gtft.py
gametheorylab/axelrod_interactive/strategies/always_cooperate.py
gametheorylab/axelrod_interactive/strategies/always_defect.py
gametheorylab/axelrod_interactive/strategies/bayesian_tit_for_tat.py
gametheorylab/axelrod_interactive/strategies/coin_flip.py
gametheorylab/axelrod_interactive/strategies/generous_tit_for_tat.py
gametheorylab/axelrod_interactive/strategies/gradual.py
gametheorylab/axelrod_interactive/strategies/grim_attacker.py
gametheorylab/axelrod_interactive/strategies/grim_trigger.py
gametheorylab/axelrod_interactive/strategies/hard_majority.py
gametheorylab/axelrod_interactive/strategies/joss.py
gametheorylab/axelrod_interactive/strategies/pavlov.py
gametheorylab/axelrod_interactive/strategies/pavlov_variant.py
gametheorylab/axelrod_interactive/strategies/reverse_tit_for_tat.py
gametheorylab/axelrod_interactive/strategies/soft_grim.py
gametheorylab/axelrod_interactive/strategies/soft_majority.py
gametheorylab/axelrod_interactive/strategies/suspicious_tit_for_tat.py
gametheorylab/axelrod_interactive/strategies/tit_for_k_tats.py
gametheorylab/axelrod_interactive/strategies/tit_for_tat.py
gametheorylab/axelrod_interactive/strategies/tranquilizer.py
gametheorylab/axelrod_interactive/strategies/user.py
game_theory_lab-0.1.3.dist-info/METADATA
game_theory_lab-0.1.3.dist-info/WHEEL
game_theory_lab-0.1.3.dist-info/top_level.txt
game_theory_lab-0.1.3.dist-info/RECORD
