Metadata-Version: 2.4
Name: game-theory-lab
Version: 0.1.3
Summary: A Python-based simulation library that enables users to directly engage with Game Theory principles through several cooperation/competition games.
Author-email: Ayomide Olumide-Attah <ayomideattah369@email.com>
License-Expression: MIT
Project-URL: Homepage, https://github.com/AyomideOlumideAttah/gametheorylab
Requires-Python: >=3.9
License-File: LICENSE.md
Requires-Dist: pandas<2.3,>=1.5
Dynamic: license-file
